LICENSE
MANIFEST.in
README.rst
setup.cfg
setup.py
Flask_DebugToolbar_Mongo.egg-info/PKG-INFO
Flask_DebugToolbar_Mongo.egg-info/SOURCES.txt
Flask_DebugToolbar_Mongo.egg-info/dependency_links.txt
Flask_DebugToolbar_Mongo.egg-info/not-zip-safe
Flask_DebugToolbar_Mongo.egg-info/top_level.txt
flask_debugtoolbar_mongo/__init__.py
flask_debugtoolbar_mongo/jinja_filters.py
flask_debugtoolbar_mongo/operation_tracker.py
flask_debugtoolbar_mongo/panel.py
flask_debugtoolbar_mongo/templates/mongo-panel.html
flask_debugtoolbar_mongo/templates/mongo-panes-subtitle.html