Metadata-Version: 1.1
Name: Flask-DebugToolbar-Mongo
Version: 0.1
Summary: MongoDB panel for the Flask Debug Toolbar
Home-page: https://github.com/bcarlin/flask-debugtoolbar-mongo
Author: Bruno Carlin
Author-email: bruno@bcarlin.net
License: MIT
Platform: UNKNOWN
Classifier: Development Status :: 3 - Alpha
Classifier: Environment :: Web Environment
Classifier: Intended Audience :: Developers
Classifier: License :: OSI Approved :: MIT License
Classifier: Operating System :: OS Independent
Classifier: Programming Language :: Python
Classifier: Topic :: Database
Classifier: Topic :: Software Development :: Libraries :: Python Modules
